{
  "type": "malum:spirit_infusion",
  "extra_items": [
    {
      "count": 4,
      "item": "minecraft:torch"
    },
    {
      "count": 1,
      "item": "aether:ambrosium_block"
    },
    {
      "count": 1,
      "item": "forbidden_arcanus:darkstone_upgrade_smithing_template"
    }
  ],
  "input": {
    "count": 1,
    "item": "morebows:iron_bow"
  },
  "output": {
    "count": 1,
    "item": "too_many_bows:torchbearer"
  },
  "spirits": [
    {
      "type": "infernal",
      "count": 8
    },
    {
      "type": "arcane",
      "count": 4
    },
    {
      "type": "aerial",
      "count": 4
    }
  ]
}