{
  "type": "minecraft:block",
  "pools": [
    {
      "rolls": {
        "min": 4,
        "max": 8
      },
      "entries": [
        {
          "type": "minecraft:item",
          "name": "minecraft:coal_ore",
          "weight": 1,
          "conditions": [
            {
              "condition": "minecraft:inverted",
              "term": {
                "condition": "minecraft:match_tool",
                "predicate": {
                  "enchantments": [
                    {
                      "enchantment": "minecraft:silk_touch",
                      "levels": {
                        "min": 1
                      }
                    }
                  ]
                }
              }
            }
          ],
          "functions": [
            {
              "function": "set_count",
              "count": {
                "min": 8,
                "max": 16
              }
            }
          ]
        },
        {
          "type": "minecraft:item",
          "name": "minecraft:iron_ore",
          "weight": 1,
          "conditions": [
            {
              "condition": "minecraft:inverted",
              "term": {
                "condition": "minecraft:match_tool",
                "predicate": {
                  "enchantments": [
                    {
                      "enchantment": "minecraft:silk_touch",
                      "levels": {
                        "min": 1
                      }
                    }
                  ]
                }
              }
            }
          ],
          "functions": [
            {
              "function": "set_count",
              "count": {
                "min": 8,
                "max": 16
              }
            }
          ]
        },
        {
          "type": "minecraft:item",
          "name": "minecraft:gold_ore",
          "weight": 1,
          "conditions": [
            {
              "condition": "minecraft:inverted",
              "term": {
                "condition": "minecraft:match_tool",
                "predicate": {
                  "enchantments": [
                    {
                      "enchantment": "minecraft:silk_touch",
                      "levels": {
                        "min": 1
                      }
                    }
                  ]
                }
              }
            }
          ],
          "functions": [
            {
              "function": "set_count",
              "count": {
                "min": 8,
                "max": 16
              }
            }
          ]
        },
        {
          "type": "minecraft:item",
          "name": "minecraft:diamond_ore",
          "weight": 1,
          "conditions": [
            {
              "condition": "minecraft:inverted",
              "term": {
                "condition": "minecraft:match_tool",
                "predicate": {
                  "enchantments": [
                    {
                      "enchantment": "minecraft:silk_touch",
                      "levels": {
                        "min": 1
                      }
                    }
                  ]
                }
              }
            }
          ],
          "functions": [
            {
              "function": "set_count",
              "count": {
                "min": 4,
                "max": 8
              }
            }
          ]
        },
        {
          "type": "minecraft:item",
          "name": "minecraft:deepslate_redstone_ore",
          "weight": 1,
          "conditions": [
            {
              "condition": "minecraft:inverted",
              "term": {
                "condition": "minecraft:match_tool",
                "predicate": {
                  "enchantments": [
                    {
                      "enchantment": "minecraft:silk_touch",
                      "levels": {
                        "min": 1
                      }
                    }
                  ]
                }
              }
            }
          ],
          "functions": [
            {
              "function": "set_count",
              "count": {
                "min": 8,
                "max": 16
              }
            }
          ]
        },
        {
          "type": "minecraft:item",
          "name": "minecraft:lapis_ore",
          "weight": 1,
          "conditions": [
            {
              "condition": "minecraft:inverted",
              "term": {
                "condition": "minecraft:match_tool",
                "predicate": {
                  "enchantments": [
                    {
                      "enchantment": "minecraft:silk_touch",
                      "levels": {
                        "min": 1
                      }
                    }
                  ]
                }
              }
            }
          ],
          "functions": [
            {
              "function": "set_count",
              "count": {
                "min": 8,
                "max": 16
              }
            }
          ]
        },
        {
          "type": "minecraft:item",
          "name": "minecraft:emerald_ore",
          "weight": 1,
          "conditions": [
            {
              "condition": "minecraft:inverted",
              "term": {
                "condition": "minecraft:match_tool",
                "predicate": {
                  "enchantments": [
                    {
                      "enchantment": "minecraft:silk_touch",
                      "levels": {
                        "min": 1
                      }
                    }
                  ]
                }
              }
            }
          ],
          "functions": [
            {
              "function": "set_count",
              "count": {
                "min": 4,
                "max": 8
              }
            }
          ]
        },
        {
          "type": "minecraft:item",
          "name": "minecraft:ancient_debris",
          "weight": 1,
          "conditions": [
            {
              "condition": "minecraft:inverted",
              "term": {
                "condition": "minecraft:match_tool",
                "predicate": {
                  "enchantments": [
                    {
                      "enchantment": "minecraft:silk_touch",
                      "levels": {
                        "min": 1
                      }
                    }
                  ]
                }
              }
            }
          ],
          "functions": [
            {
              "function": "set_count",
              "count": {
                "min": 2,
                "max": 4
              }
            }
          ]
        }
      ]
    },
    {
      "rolls": {
        "min": 4,
        "max": 8
      },
      "entries": [
        {
          "type": "minecraft:item",
          "name": "reliquary:glowing_bread",
          "weight": 5,
          "conditions": [
            {
              "condition": "minecraft:inverted",
              "term": {
                "condition": "minecraft:match_tool",
                "predicate": {
                  "enchantments": [
                    {
                      "enchantment": "minecraft:silk_touch",
                      "levels": {
                        "min": 1
                      }
                    }
                  ]
                }
              }
            }
          ],
          "functions": [
            {
              "function": "set_count",
              "count": {
                "min": 6,
                "max": 24
              }
            }
          ]
        },
        {
          "type": "minecraft:item",
          "name": "minecraft:gunpowder",
          "weight": 5,
          "conditions": [
            {
              "condition": "minecraft:inverted",
              "term": {
                "condition": "minecraft:match_tool",
                "predicate": {
                  "enchantments": [
                    {
                      "enchantment": "minecraft:silk_touch",
                      "levels": {
                        "min": 1
                      }
                    }
                  ]
                }
              }
            }
          ],
          "functions": [
            {
              "function": "set_count",
              "count": {
                "min": 6,
                "max": 18
              }
            }
          ]
        },
        {
          "type": "minecraft:item",
          "name": "domesticationinnovation:rotten_apple",
          "weight": 1,
          "conditions": [
            {
              "condition": "minecraft:inverted",
              "term": {
                "condition": "minecraft:match_tool",
                "predicate": {
                  "enchantments": [
                    {
                      "enchantment": "minecraft:silk_touch",
                      "levels": {
                        "min": 1
                      }
                    }
                  ]
                }
              }
            }
          ],
          "functions": [
            {
              "function": "set_count",
              "count": {
                "min": 4,
                "max": 8
              }
            }
          ]
        }
      ]
    },
    {
      "rolls": 1,
      "entries": [
        {
          "type": "minecraft:item",
          "name": "minecraft:diamond_pickaxe",
          "weight": 10,
          "conditions": [
            {
              "condition": "minecraft:inverted",
              "term": {
                "condition": "minecraft:match_tool",
                "predicate": {
                  "enchantments": [
                    {
                      "enchantment": "minecraft:silk_touch",
                      "levels": {
                        "min": 1
                      }
                    }
                  ]
                }
              }
            }
          ],
          "functions": [
            {
              "function": "set_count",
              "count": {
                "min": 1,
                "max": 1
              }
            },
            {
              "function": "enchant_with_levels",
              "treasure": true,
              "levels": {
                "min": 30,
                "max": 100
              }
            }
          ]
        },
        {
          "type": "minecraft:item",
          "name": "call_of_yucutan:golden_torch",
          "weight": 40,
          "conditions": [
            {
              "condition": "minecraft:inverted",
              "term": {
                "condition": "minecraft:match_tool",
                "predicate": {
                  "enchantments": [
                    {
                      "enchantment": "minecraft:silk_touch",
                      "levels": {
                        "min": 1
                      }
                    }
                  ]
                }
              }
            }
          ],
          "functions": [
            {
              "function": "set_count",
              "count": {
                "min": 16,
                "max": 32
              }
            }
          ]
        },
        {
          "type": "minecraft:item",
          "name": "call_of_yucutan:bone_torch",
          "weight": 40,
          "conditions": [
            {
              "condition": "minecraft:inverted",
              "term": {
                "condition": "minecraft:match_tool",
                "predicate": {
                  "enchantments": [
                    {
                      "enchantment": "minecraft:silk_touch",
                      "levels": {
                        "min": 1
                      }
                    }
                  ]
                }
              }
            }
          ],
          "functions": [
            {
              "function": "set_count",
              "count": {
                "min": 16,
                "max": 32
              }
            }
          ]
        },
        {
          "type": "minecraft:item",
          "name": "minecraft:enchanted_golden_apple",
          "weight": 1,
          "conditions": [
            {
              "condition": "minecraft:inverted",
              "term": {
                "condition": "minecraft:match_tool",
                "predicate": {
                  "enchantments": [
                    {
                      "enchantment": "minecraft:silk_touch",
                      "levels": {
                        "min": 1
                      }
                    }
                  ]
                }
              }
            }
          ],
          "functions": [
            {
              "function": "set_count",
              "count": {
                "min": 1,
                "max": 1
              }
            }
          ]
        }
      ]
    },
    {
      "rolls": 1,
      "entries": [
        {
          "type": "minecraft:item",
          "name": "infinite_abyss:iron_crate",
          "weight": 1,
          "conditions": [
            {
              "condition": "minecraft:match_tool",
              "predicate": {
                "enchantments": [
                  {
                    "enchantment": "minecraft:silk_touch",
                    "levels": {
                      "min": 1
                    }
                  }
                ]
              }
            }
          ],
          "functions": [
            {
              "function": "set_count",
              "count": {
                "min": 1,
                "max": 1
              }
            }
          ]
        }
      ]
    },
    {
      "rolls": {
        "min": 2,
        "max": 4
      },
      "entries": [
        {
          "type": "minecraft:item",
          "name": "infinite_abyss:violet_diamond",
          "weight": 10,
          "functions": [
            {
              "function": "set_count",
              "count": {
                "min": 4,
                "max": 8
              }
            }
          ]
        },
        {
          "type": "minecraft:item",
          "name": "minecraft:prismarine_shard",
          "weight": 10,
          "functions": [
            {
              "function": "set_count",
              "count": {
                "min": 4,
                "max": 8
              }
            }
          ]
        }
      ]
    },
    {
      "rolls": 1,
      "entries": [
        {
          "type": "minecraft:item",
          "name": "locusazzurro_icaruswings:steel_ingot",
          "weight": 10,
          "functions": [
            {
              "function": "set_count",
              "count": {
                "min": 8,
                "max": 32
              }
            }
          ]
        }
      ]
    }
  ],
  "random_sequence": "infinite_abyss:blocks/iron_crate"
}